pyhpke/__init__.py
pyhpke/aead.py
pyhpke/aead_interface.py
pyhpke/aead_key.py
pyhpke/aead_key_interface.py
pyhpke/cipher_suite.py
pyhpke/consts.py
pyhpke/context_interface.py
pyhpke/encryption_context.py
pyhpke/exceptions.py
pyhpke/exporter_context.py
pyhpke/kdf.py
pyhpke/kdf_interface.py
pyhpke/kem.py
pyhpke/kem_interface.py
pyhpke/kem_key.py
pyhpke/kem_key_interface.py
pyhpke/kem_primitives/__init__.py
pyhpke/kem_primitives/ec.py
pyhpke/kem_primitives/x25519.py
pyhpke/kem_primitives/x448.py
pyhpke/kem_primitives_interface.py
pyhpke/keys/__init__.py
pyhpke/keys/aes_gcm_key.py
pyhpke/keys/chacha20_poly1305_key.py
pyhpke/keys/ec_key.py
pyhpke/keys/x25519_key.py
pyhpke/keys/x448_key.py
pyhpke/py.typed
pyhpke/recipient_context.py
pyhpke/sender_context.py
pyhpke/utils.py
pyhpke-0.6.3.dist-info/METADATA
pyhpke-0.6.3.dist-info/WHEEL
pyhpke-0.6.3.dist-info/licenses/LICENSE
pyhpke-0.6.3.dist-info/RECORD
