Metadata-Version: 2.4
Name: pyhpke
Version: 0.6.3
Summary: A Python implementation of HPKE.
License: MIT
License-File: LICENSE
Author: Ajitomi Daisuke
Author-email: dajiaji@gmail.com
Requires-Python: >=3.9,<4.0
Classifier: License :: OSI Approved :: MIT License
Classifier: Programming Language :: Python :: 3
Classifier: Programming Language :: Python :: 3.9
Classifier: Programming Language :: Python :: 3.10
Classifier: Programming Language :: Python :: 3.11
Classifier: Programming Language :: Python :: 3.12
Classifier: Programming Language :: Python :: 3.13
Classifier: Programming Language :: Python :: 3.14
Requires-Dist: cryptography (>=42.0.1,<47)
Project-URL: Repository, https://github.com/dajiaji/pyhpke
